[
  {
    "user": {
      "name": "Roger Federer",
      "avatars": "https://i.imgur.com/73hZDYK.png",
      "handle": "@TennisGoat"
    },
    "content": {
      "text": "Looking forward to winning Wimbledon for the 47th time this year!"
    },
    "created_at": 1651047504964
  },
  {
    "user": {
      "name": "Joker",
      "avatars": "https://i.imgur.com/nlhLi3I.png",
      "handle": "@Mr.Smile"
    },
    "content": {
      "text": "You wouldn't get it"
    },
    "created_at": 1651133904964
  }
]